[
  {
    "relation": [
      "delegate_permission/common.handle_all_urls",
      "delegate_permission/common.get_login_creds"
    ],
    "target": {
      "namespace": "android_app",
      "package_name": "online.newinternet.app",
      "sha256_cert_fingerprints": [
        "DB:82:81:56:5E:6B:63:04:8C:2E:6C:9F:43:2A:DB:6B:AB:3F:45:CA:7A:BB:74:B7:70:10:ED:CF:26:79:62:16",
        "70:F9:2F:B7:85:D4:E5:26:7C:8D:D6:FF:5A:DE:A1:1E:53:C3:10:D3:EA:7D:E0:27:05:F1:9B:1A:04:E0:84:8B"
      ]
    }
  }
]